wpa2slow/handshake.py
wpa2slow/compare.py
wpa2slow/pbkdf2.py
wpa2slow/wpa2.py
wpa2slow/sha1.py
wpa2slow/__init__.py
wpa2slow/hmac_sha1.py
wpa2slow-0.4.dist-info/DESCRIPTION.rst
wpa2slow-0.4.dist-info/metadata.json
wpa2slow-0.4.dist-info/METADATA
wpa2slow-0.4.dist-info/top_level.txt
wpa2slow-0.4.dist-info/RECORD
wpa2slow-0.4.dist-info/LICENSE.txt
wpa2slow-0.4.dist-info/WHEEL
