Metadata-Version: 2.0
Name: wpa2slow
Version: 0.4
Summary: A full Python implementation of the WPA2 encryption algorithm, using no encryption libraries.
Home-page: http://github.com/JarrettR/WPA-Slowed-Down
Author: Jarrett Rainier
Author-email: jrainier@gmail.com
License: GPLv3
Platform: UNKNOWN
Classifier: Development Status :: 3 - Alpha
Classifier: Intended Audience :: Developers
Classifier: Natural Language :: English
Classifier: License :: OSI Approved :: GNU General Public License v3 (GPLv3)
Classifier: Operating System :: OS Independent
Classifier: Programming Language :: Python
Classifier: Programming Language :: Python :: 2
Classifier: Programming Language :: Python :: 2.7
Classifier: Topic :: Security :: Cryptography
